wkwebview.py
pythonista_wkwebview-1.0.dist-info/LICENSE
pythonista_wkwebview-1.0.dist-info/WHEEL
pythonista_wkwebview-1.0.dist-info/METADATA
pythonista_wkwebview-1.0.dist-info/RECORD
