Metadata-Version: 2.1
Name: pythonista-wkwebview
Version: 1.0
Summary: WKWebView - modern webview for Pythonista
Home-page: https://github.com/mikaelho/pythonista-webview
License: TheUnlicense
Author: Mikael Honkala
Author-email: mikael.honkala@gmail.com
Classifier: Operating System :: iOS
